freddi/evolution_result.py
freddi/__init__.py
freddi/_freddi.cpython-37m-x86_64-linux-gnu.so
freddi-2.0.0.dist-info/METADATA
freddi-2.0.0.dist-info/WHEEL
freddi-2.0.0.dist-info/RECORD
freddi-2.0.0.dist-info/top_level.txt
