Metadata-Version: 2.1
Name: freddi
Version: 2.0.0
Summary: Compute FRED light curves of LMXBs outbursts
Home-page: http://xray.sai.msu.ru/~malanchev/freddi/
Author: Konstantin Malanchev
Author-email: malanchev@sai.msu.ru
License: GPLv3
Keywords: science astrophysics accretion
Classifier: Intended Audience :: Science/Research
Classifier: License :: OSI Approved :: MIT License
Classifier: Programming Language :: Python :: 3
Classifier: Programming Language :: Python :: 3.7
Classifier: Programming Language :: Python :: 3.8
Classifier: Programming Language :: Python :: 3.9
Classifier: Programming Language :: Python :: 3.10
Classifier: Programming Language :: Python :: 3.11
Classifier: Programming Language :: Python :: 3.12
Classifier: Programming Language :: Python :: 3 :: Only
Classifier: Topic :: Scientific/Engineering :: Physics
Requires-Python: >=3.7
Requires-Dist: numpy
